[{"id":1,"name":"Genesis","shortname":"Gn","testament":"Old"},{"id":2,"name":"Exodus","shortname":"Ex","testament":"Old"},{"id":3,"name":"Leviticus","shortname":"Lv","testament":"Old"},{"id":4,"name":"Numbers","shortname":"Nm","testament":"Old"},{"id":5,"name":"Deuteronomy","shortname":"Dt","testament":"Old"},{"id":6,"name":"Joshua","shortname":"Jo","testament":"Old"},{"id":7,"name":"Judges","shortname":"Jgs","testament":"Old"},{"id":8,"name":"Ruth","shortname":"Ru","testament":"Old"},{"id":9,"name":"1 Samuel","shortname":"1 Sm","testament":"Old"},{"id":10,"name":"2 Samuel","shortname":"2 Sm","testament":"Old"},{"id":11,"name":"1 Kings","shortname":"1 Kgs","testament":"Old"},{"id":12,"name":"2 Kings","shortname":"2 Kgs","testament":"Old"},{"id":13,"name":"1 Chronicles","shortname":"1 Chr","testament":"Old"},{"id":14,"name":"2 Chronicles","shortname":"2 Chr","testament":"Old"},{"id":15,"name":"Ezra","shortname":"Ezr","testament":"Old"},{"id":16,"name":"Nehemiah","shortname":"Neh","testament":"Old"},{"id":17,"name":"Esther","shortname":"Est","testament":"Old"},{"id":18,"name":"Job","shortname":"Jb","testament":"Old"},{"id":19,"name":"Psalms","shortname":"Ps","testament":"Old"},{"id":20,"name":"Proverbs","shortname":"Prv","testament":"Old"},{"id":21,"name":"Ecclesiastes","shortname":"Eccl","testament":"Old"},{"id":22,"name":"Song of Solomon","shortname":"Sg","testament":"Old"},{"id":23,"name":"Isaiah","shortname":"Is","testament":"Old"},{"id":24,"name":"Jeremiah","shortname":"Jer","testament":"Old"},{"id":25,"name":"Lamentations","shortname":"Lam","testament":"Old"},{"id":26,"name":"Ezekiel","shortname":"Ez","testament":"Old"},{"id":27,"name":"Daniel","shortname":"Dn","testament":"Old"},{"id":28,"name":"Hosea","shortname":"Hos","testament":"Old"},{"id":29,"name":"Joel","shortname":"Jl","testament":"Old"},{"id":30,"name":"Amos","shortname":"Am","testament":"Old"},{"id":31,"name":"Obadiah","shortname":"Ob","testament":"Old"},{"id":32,"name":"Jonah","shortname":"Jon","testament":"Old"},{"id":33,"name":"Micah","shortname":"Mi","testament":"Old"},{"id":34,"name":"Nahum","shortname":"Na","testament":"Old"},{"id":35,"name":"Habakkuk","shortname":"Hb","testament":"Old"},{"id":36,"name":"Zephaniah","shortname":"Zep","testament":"Old"},{"id":37,"name":"Haggai","shortname":"Hg","testament":"Old"},{"id":38,"name":"Zechariah","shortname":"Zec","testament":"Old"},{"id":39,"name":"Malachi","shortname":"Mal","testament":"Old"},{"id":40,"name":"Matthew","shortname":"Mat","testament":"New"},{"id":41,"name":"Mark","shortname":"Mk","testament":"New"},{"id":42,"name":"Luke","shortname":"Lk","testament":"New"},{"id":43,"name":"John","shortname":"Jn","testament":"New"},{"id":44,"name":"Acts","shortname":"Ac","testament":"New"},{"id":45,"name":"Romans","shortname":"Rm","testament":"New"},{"id":46,"name":"1 Corinthians","shortname":"1 Co","testament":"New"},{"id":47,"name":"2 Corinthians","shortname":"2 Co","testament":"New"},{"id":48,"name":"Galatians","shortname":"Ga","testament":"New"},{"id":49,"name":"Ephesians","shortname":"Ep","testament":"New"},{"id":50,"name":"Philippians","shortname":"Php","testament":"New"},{"id":51,"name":"Colossians","shortname":"Col","testament":"New"},{"id":52,"name":"1 Thessalonians","shortname":"1 Th","testament":"New"},{"id":53,"name":"2 Thessalonians","shortname":"2 Th","testament":"New"},{"id":54,"name":"1 Timothy","shortname":"1 Tm","testament":"New"},{"id":55,"name":"2 Timothy","shortname":"2 Tm","testament":"New"},{"id":56,"name":"Titus","shortname":"Ti","testament":"New"},{"id":57,"name":"Philemon","shortname":"Phm","testament":"New"},{"id":58,"name":"Hebrews","shortname":"He","testament":"New"},{"id":59,"name":"James","shortname":"Jm","testament":"New"},{"id":60,"name":"1 Peter","shortname":"1 Pt","testament":"New"},{"id":61,"name":"2 Peter","shortname":"2 Pt","testament":"New"},{"id":62,"name":"1 John","shortname":"1 Jn","testament":"New"},{"id":63,"name":"2 John","shortname":"2 Jn","testament":"New"},{"id":64,"name":"3 John","shortname":"3 Jn","testament":"New"},{"id":65,"name":"Jude","shortname":"Ju","testament":"New"},{"id":66,"name":"Revelation","shortname":"Rv","testament":"New"}]